{
  "content": [
    {
      "gameId": 123,
      "homeTeamName": "두산 베어스",
      "awayTeamName": "SSG 랜더스",
      "stadiumName": "두산",
      "sportName": "야구",
      "gameStartTime": "2024-08-09T15:00:00",
      "timeOnSale": "2024-08-04T15:40:20",
      "timeOffSale": "2024-08-06T15:40:20",
      "id": "1e5d"
    },
    {
      "gameId": 124,
      "homeTeamName": "LG 트윈스",
      "awayTeamName": "KT 위즈",
      "stadiumName": "LG",
      "sportName": "야구",
      "gameStartTime": "2024-09-09T15:00:00",
      "timeOnSale": "2024-09-01T15:40:20",
      "timeOffSale": "2024-09-06T15:40:20",
      "id": "610b"
    },
    {
      "gameId": 125,
      "homeTeamName": "NC 다이노스",
      "awayTeamName": "KIA 타이거즈",
      "stadiumName": "NC",
      "sportName": "야구",
      "gameStartTime": "2024-10-09T15:00:00",
      "timeOnSale": "2024-10-04T15:40:20",
      "timeOffSale": "2024-10-06T15:40:20",
      "id": "4ee6"
    },
    {
      "gameId": 126,
      "homeTeamName": "롯데 자이언츠",
      "awayTeamName": "키움 히어로즈",
      "stadiumName": "롯데",
      "sportName": "야구",
      "gameStartTime": "2024-11-09T15:00:00",
      "timeOnSale": "2024-11-04T15:40:20",
      "timeOffSale": "2024-11-06T15:40:20",
      "id": "5faa"
    },
    {
      "gameId": 127,
      "homeTeamName": "울산 HD FC",
      "awayTeamName": "광주 FC",
      "stadiumName": "울산",
      "sportName": "축구",
      "gameStartTime": "2024-09-23T15:00:00",
      "timeOnSale": "2024-09-11T15:40:20",
      "timeOffSale": "2024-09-20T15:40:20",
      "id": "de55"
    },
    {
      "gameId": 128,
      "homeTeamName": "광주 FC",
      "awayTeamName": "포항 스틸러스",
      "stadiumName": "포항",
      "sportName": "축구",
      "gameStartTime": "2024-08-11T15:00:00",
      "timeOnSale": "2024-08-05T15:40:20",
      "timeOffSale": "2024-08-09T15:40:20",
      "id": "464e"
    }
  ],
  "matches": [
    {
      "id": "1",
      "sportName": "야구",
      "gameStartTime": "2024-08-01T15:40:00",
      "stadiumName": "고척(서울)",
      "homeTeamName": "삼성라이온즈",
      "awayTeamName": "엔씨다이노스"
    },
    {
      "id": "2",
      "sportName": "야구",
      "gameStartTime": "2024-08-15T12:30:00",
      "stadiumName": "잠실(서울)",
      "homeTeamName": "기아타이거즈",
      "awayTeamName": "엔씨다이노스"
    },
    {
      "id": "3",
      "sportName": "야구",
      "gameStartTime": "2024-09-01T15:40:00",
      "stadiumName": "대구",
      "homeTeamName": "광주 FC",
      "awayTeamName": "KT 위즈"
    },
    {
      "id": "4",
      "sportName": "야구",
      "gameStartTime": "2024-08-29T15:40:00",
      "stadiumName": "포항",
      "homeTeamName": "삼성라이온즈",
      "awayTeamName": "SSG 랜더스"
    },
    {
      "id": "5",
      "sportName": "야구",
      "gameStartTime": "2024-08-08T15:40:00",
      "stadiumName": "울산",
      "homeTeamName": "롯데 자이언츠",
      "awayTeamName": "엔씨다이노스"
    },
    {
      "id": "6",
      "sportName": "축구",
      "gameStartTime": "2024-08-06T15:40:00",
      "stadiumName": "울산",
      "homeTeamName": "울산 현대",
      "awayTeamName": "포항 스틸러스"
    },
    {
      "id": "7",
      "sportName": "축구",
      "gameStartTime": "2024-08-19T15:40:00",
      "stadiumName": "전북",
      "homeTeamName": "전북 현대 모터스",
      "awayTeamName": "FC 서울"
    },
    {
      "id": "8",
      "sportName": "축구",
      "gameStartTime": "2024-09-05T15:40:00",
      "stadiumName": "포항",
      "homeTeamName": "포항 스틸러스",
      "awayTeamName": "인천 유나이티드"
    },
    {
      "id": "2672",
      "sportName": "축구",
      "gameStartTime": "2024-09-05T15:40:00",
      "stadiumName": "울산",
      "homeTeamName": "울산 현대",
      "awayTeamName": "수원 삼성 블루윙즈"
    },
    {
      "id": "5956",
      "sportName": "야구",
      "gameStartTime": "2024-08-10T12:30",
      "stadiumName": "고척(서울)",
      "homeTeamName": "LG 트윈스",
      "awayTeamName": "SSG 랜더스"
    },
    {
      "id": "dfda",
      "sportName": "야구",
      "gameStartTime": "2024-08-16T12:30",
      "stadiumName": "사직(부산)",
      "homeTeamName": "롯데 자이언츠",
      "awayTeamName": "SSG 랜더스"
    },
    {
      "sportName": "야구",
      "gameStartTime": "2024-08-30T15:24",
      "stadiumName": "대구",
      "homeTeamName": "한화 이글스",
      "awayTeamName": "NC 다이노스",
      "id": "Ovtx9jd"
    },
    {
      "sportName": "축구",
      "gameStartTime": "2024-09-28T22:30",
      "stadiumName": "전북",
      "homeTeamName": "전북 현대 모터스",
      "awayTeamName": "FC 서울",
      "id": "_XDuz13"
    },
    {
      "sportName": "야구",
      "gameStartTime": "2024-09-21T12:28",
      "stadiumName": "잠실(서울)",
      "homeTeamName": "2",
      "awayTeamName": "1",
      "id": "DZnytLf"
    },
    {
      "sportName": "축구",
      "gameStartTime": "2024-10-12T16:53",
      "stadiumName": "전북",
      "homeTeamName": "2",
      "awayTeamName": "8",
      "id": "ME_3x1P"
    },
    {
      "id": "96a8",
      "sportName": "야구",
      "gameStartTime": "2024-10-12T16:36",
      "stadiumName": "대구",
      "homeTeamName": "4",
      "awayTeamName": "2"
    }
  ],
  "reservations": [
    {
      "gameId": 124,
      "homeTeamName": "LG 트윈스",
      "awayTeamName": "KT 위즈",
      "stadiumName": "서울종합운동장 잠실야구장",
      "sportName": "야구",
      "gameStartTime": "2024-09-09T15:00:00",
      "reservationStatus": true,
      "id": 7393
    },
    {
      "gameId": 144,
      "homeTeamName": "LG 트윈스",
      "awayTeamName": "KT 위즈",
      "stadiumName": "서울종합운동장 잠실야구장",
      "sportName": "야구",
      "gameStartTime": "2024-09-09T15:00:00",
      "reservationStatus": true,
      "id": 7394
    },
    {
      "gameId": 114,
      "homeTeamName": "SSG 랜더스",
      "awayTeamName": "KIA 타이거즈",
      "stadiumName": "서울종합운동장 잠실야구장",
      "sportName": "야구",
      "gameStartTime": "2024-09-09T15:00:00",
      "reservationStatus": true,
      "id": 7395
    },
    {
      "gameId": 164,
      "homeTeamName": "LG 트윈스",
      "awayTeamName": "KT 위즈",
      "stadiumName": "서울종합운동장 잠실야구장",
      "sportName": "야구",
      "gameStartTime": "2024-09-09T15:00:00",
      "reservationStatus": true,
      "id": 7396
    }
  ],
  "reservation": [
    {
      "id": 7393,
      "homeTeamName": "LG 트윈스",
      "awayTeamName": "KT 위즈",
      "gameStartTime": "2024-09-09T15:00:00",
      "stadiumName": "서울종합운동장 잠실야구장",
      "reservationStatus": "COMPLETE",
      "totalPrice": "173,000 원",
      "createDate": "2024-08-24T16:13:00",
      "memberName": "홍길동님",
      "seat": [
        {
          "seatPosition": "1루",
          "seatRow": "3열",
          "seatNumber": "41번"
        },
        {
          "seatPosition": "프리미엄",
          "seatRow": "1열",
          "seatNumber": "1번"
        },
        {
          "seatPosition": "프리미엄",
          "seatRow": "2열",
          "seatNumber": "3번"
        },
        {
          "seatPosition": "외야",
          "seatRow": "2열",
          "seatNumber": "55번"
        },
        {
          "seatPosition": "3루",
          "seatRow": "2열",
          "seatNumber": "3번"
        },
        {
          "seatPosition": "1루",
          "seatRow": "2열",
          "seatNumber": "33번"
        }
      ]
    },
    {
      "id": 7394,
      "homeTeamName": "LG 트윈스",
      "awayTeamName": "KT 위즈",
      "gameStartTime": "2024-09-09T15:00:00",
      "stadiumName": "서울종합운동장 잠실야구장",
      "reservationStatus": "COMPLETE",
      "totalPrice": "173,000 원",
      "createDate": "2024-08-24T16:13:00",
      "memberName": "홍길동님",
      "seat": [
        {
          "seatPosition": "1루",
          "seatRow": "3열",
          "seatNumber": "41번"
        },
        {
          "seatPosition": "프리미엄",
          "seatRow": "1열",
          "seatNumber": "1번"
        },
        {
          "seatPosition": "프리미엄",
          "seatRow": "2열",
          "seatNumber": "3번"
        },
        {
          "seatPosition": "외야",
          "seatRow": "2열",
          "seatNumber": "55번"
        },
        {
          "seatPosition": "3루",
          "seatRow": "2열",
          "seatNumber": "3번"
        },
        {
          "seatPosition": "1루",
          "seatRow": "2열",
          "seatNumber": "33번"
        }
      ]
    },
    {
      "id": 7395,
      "homeTeamName": "SSG 랜더스",
      "awayTeamName": "KIA 타이거즈",
      "gameStartTime": "2024-09-09T15:00:00",
      "stadiumName": "광주 챔피언스 필드",
      "reservationStatus": "COMPLETE",
      "totalPrice": "173,000 원",
      "createDate": "2024-09-09T15:00:00",
      "memberName": "홍길동님",
      "seat": [
        {
          "seatPosition": "1루",
          "seatRow": "3열",
          "seatNumber": "41번"
        },
        {
          "seatPosition": "프리미엄",
          "seatRow": "1열",
          "seatNumber": "1번"
        },
        {
          "seatPosition": "프리미엄",
          "seatRow": "2열",
          "seatNumber": "3번"
        },
        {
          "seatPosition": "외야",
          "seatRow": "2열",
          "seatNumber": "55번"
        },
        {
          "seatPosition": "3루",
          "seatRow": "2열",
          "seatNumber": "3번"
        },
        {
          "seatPosition": "1루",
          "seatRow": "2열",
          "seatNumber": "33번"
        }
      ]
    },
    {
      "id": 7396,
      "homeTeamName": "LG 트윈스",
      "awayTeamName": "KT 위즈",
      "gameStartTime": "2024-09-09T15:00:00",
      "stadiumName": "서울종합운동장 잠실야구장",
      "reservationStatus": "COMPLETE",
      "totalPrice": "173,000 원",
      "createDate": "2024-09-09T15:00:00",
      "memberName": "홍길동님",
      "seat": [
        {
          "seatPosition": "1루",
          "seatRow": "3열",
          "seatNumber": "41번"
        },
        {
          "seatPosition": "프리미엄",
          "seatRow": "1열",
          "seatNumber": "1번"
        },
        {
          "seatPosition": "프리미엄",
          "seatRow": "2열",
          "seatNumber": "3번"
        },
        {
          "seatPosition": "외야",
          "seatRow": "2열",
          "seatNumber": "55번"
        },
        {
          "seatPosition": "3루",
          "seatRow": "2열",
          "seatNumber": "3번"
        },
        {
          "seatPosition": "1루",
          "seatRow": "2열",
          "seatNumber": "33번"
        }
      ]
    }
  ],
  "login": [
    {
      "id": "1",
      "username": "johndoe",
      "password": "password123",
      "accessToken": "sampleAccessToken123",
      "refreshToken": "sampleRefreshToken123"
    },
    {
      "id": "9997",
      "email": "ddhhss0603@gmail.com",
      "password": "dhshappy1995!"
    },
    {
      "id": "8c71",
      "email": "dhs0603@naver.com",
      "password": "dhshappy1995!"
    },
    {
      "id": "9be4",
      "email": "ddhhss0603@gmail.com",
      "password": "dhshappy1995!"
    },
    {
      "id": "1ded",
      "email": "ddhhss0603@gmail.com",
      "password": "dhshappy1995!"
    },
    {
      "id": "45d8",
      "email": "ddhhss0603@gmail.com",
      "password": "dhshappy1995!"
    },
    {
      "id": "6550",
      "email": "ddhhss0603@gmail.com",
      "password": "dhshappy1995!"
    },
    {
      "id": "cddc",
      "email": "ddhhss0603@gmail.com",
      "password": "dhshappy1995!"
    },
    {
      "id": "92e5",
      "email": "dhs0603@naver.com",
      "password": "dhshappy1995!"
    },
    {
      "id": "db55",
      "email": "ddhhss0603@gmail.com",
      "password": "dhshappy1995!"
    }
  ],
  "seats": [
    {
      "homeTeamName": "두산베어스",
      "awayTeamName": "KIA 타이거즈",
      "stadiumName": "고척(서울)",
      "gameStartTime": "2024-08-01T15:40:00",
      "content": [
        {
          "seatPosition": "1루",
          "seatPrice": "12000"
        },
        {
          "seatPosition": "2루",
          "seatPrice": "12000"
        },
        {
          "seatPosition": "외야",
          "seatPrice": "12000"
        },
        {
          "seatPosition": "프리미엄",
          "seatPrice": "24000"
        }
      ],
      "id": "da4d"
    },
    {
      "seat": ["seatId"],
      "id": "048d"
    }
  ],
  "pay": [
    {
      "id": "aebe",
      "totalPrice": "72,000",
      "seatIds": ["프리미엄 4열 40번", "프리미엄 4열 39번", "프리미엄 4열 38번"]
    },
    {
      "id": "96c2",
      "totalPrice": "24,000",
      "seatIds": ["외야 4열 40번", "외야 4열 39번"]
    },
    {
      "id": "f548",
      "totalPrice": "36,000",
      "seatIds": ["외야 4열 38번", "외야 4열 37번", "외야 4열 36번"]
    }
  ]
}
